copula_wrapper/__init__.py
copula_wrapper/correlation_convert.py
copula_wrapper/joint_distribution.py
copula_wrapper-0.1.6.dist-info/METADATA
copula_wrapper-0.1.6.dist-info/WHEEL
copula_wrapper-0.1.6.dist-info/RECORD
