Metadata-Version: 2.1
Name: copula-wrapper
Version: 0.1.6
Summary: Top-level package for statsmodels copula wrapper.
Home-page: https://github.com/tadamcz/copula-wrapper
Author: Tom Adamczewski
Author-email: tadamczewskipublic@gmail.com
Requires-Python: >=3.9,<3.13
Classifier: Natural Language :: English
Classifier: Programming Language :: Python :: 3
Classifier: Programming Language :: Python :: 3.9
Classifier: Programming Language :: Python :: 3.10
Classifier: Programming Language :: Python :: 3.11
Requires-Dist: numpy (>=1.23.0,<2.0.0)
Requires-Dist: pandas (>=2.0.3,<3.0.0)
Requires-Dist: scipy (>=1.11.0,<2.0.0)
Requires-Dist: statsmodels (>=0.14.0)
